LICENSE.txt
MANIFEST.in
README.rst
setup.cfg
setup.py
pymco/__init__.py
pymco/config.py
pymco/exc.py
pymco/listener.py
pymco/message.py
pymco/rpc.py
pymco/utils.py
pymco/connector/__init__.py
pymco/connector/activemq.py
pymco/connector/rabbitmq.py
pymco/connector/stomp.py
pymco/security/__init__.py
pymco/security/none.py
pymco/security/ssl.py
pymco/serializers/__init__.py
pymco/serializers/yaml.py
pymco/test/__init__.py
pymco/test/ctxt.py
pymco/test/utils.py
pymco/test/templates/server.cfg.jinja
python_mcollective.egg-info/PKG-INFO
python_mcollective.egg-info/SOURCES.txt
python_mcollective.egg-info/dependency_links.txt
python_mcollective.egg-info/requires.txt
python_mcollective.egg-info/top_level.txt
requirements/base.txt
requirements/docs.txt
requirements/flake8.txt
requirements/mac.tests.txt
requirements/tests.txt