Metadata-Version: 1.1
Name: python-mcollective
Version: 0.0.1.dev4
Summary: Python bindings for MCollective
Home-page: https://github.com/rafaduran/python-mcollective
Author: Rafael Durán Castañeda
Author-email: rafadurancastaneda@gmail.com
License: BSD
Keywords: MCollective
Platform: UNKNOWN
Classifier: Development Status :: 1 - Planning
Classifier: Intended Audience :: Developers
Classifier: License :: OSI Approved :: BSD License
Classifier: Operating System :: OS Independent
Classifier: Programming Language :: Python :: 2
Classifier: Programming Language :: Python :: 2.6
Classifier: Programming Language :: Python :: 2.7
Classifier: Programming Language :: Python :: 3
Classifier: Programming Language :: Python :: 3.3
Classifier: Topic :: System :: Systems Administration
